odoo8_addon_website_sale_suggest_create_account-8.0.1.0.0.99.dev10-py2.7-nspkg.pth
odoo_addons/website_sale_suggest_create_account/__openerp__.py
odoo_addons/website_sale_suggest_create_account/__init__.py
odoo_addons/website_sale_suggest_create_account/README.rst
odoo_addons/website_sale_suggest_create_account/i18n/it.po
odoo_addons/website_sale_suggest_create_account/i18n/es.po
odoo_addons/website_sale_suggest_create_account/i18n/sl.po
odoo_addons/website_sale_suggest_create_account/views/website_sale.xml
odoo_addons/website_sale_suggest_create_account/static/description/icon.png
odoo8_addon_website_sale_suggest_create_account-8.0.1.0.0.99.dev10.dist-info/top_level.txt
odoo8_addon_website_sale_suggest_create_account-8.0.1.0.0.99.dev10.dist-info/WHEEL
odoo8_addon_website_sale_suggest_create_account-8.0.1.0.0.99.dev10.dist-info/RECORD
odoo8_addon_website_sale_suggest_create_account-8.0.1.0.0.99.dev10.dist-info/metadata.json
odoo8_addon_website_sale_suggest_create_account-8.0.1.0.0.99.dev10.dist-info/DESCRIPTION.rst
odoo8_addon_website_sale_suggest_create_account-8.0.1.0.0.99.dev10.dist-info/METADATA
odoo8_addon_website_sale_suggest_create_account-8.0.1.0.0.99.dev10.dist-info/namespace_packages.txt
